LICENSE
README.md
setup.py
nonebot_plugin_kfcrazy/__init__.py
nonebot_plugin_kfcrazy.egg-info/PKG-INFO
nonebot_plugin_kfcrazy.egg-info/SOURCES.txt
nonebot_plugin_kfcrazy.egg-info/dependency_links.txt
nonebot_plugin_kfcrazy.egg-info/requires.txt
nonebot_plugin_kfcrazy.egg-info/top_level.txt