Metadata-Version: 2.1
Name: nonebot-plugin-kfcrazy
Version: 2.0.3
Summary: nonebot2 plugin kfcrazy
Home-page: https://github.com/Kaguya233qwq/nonebot_plugin_kfcrazy
Author: Kaguya233qwq
Author-email: 1435608435@qq.com
License: UNKNOWN
Keywords: pip,nonebot2,nonebot,KFC,v我50,疯狂星期四,肯德基
Platform: any
Classifier: Programming Language :: Python :: 3
Classifier: License :: OSI Approved :: GNU General Public License v3 (GPLv3)
Classifier: Natural Language :: Chinese (Simplified)
License-File: LICENSE
